README.md
setup.py
limitediterables/__init__.py
limitediterables/iterables.py
limitediterables.egg-info/PKG-INFO
limitediterables.egg-info/SOURCES.txt
limitediterables.egg-info/dependency_links.txt
limitediterables.egg-info/not-zip-safe
limitediterables.egg-info/top_level.txt