Metadata-Version: 1.0
Name: limitediterables
Version: 0.1.0
Summary: Rate limit your iterables.
Home-page: https://github.com/Poogles/limitediterables
Author: Sam Pegler
Author-email: sam@sampegler.co.uk
License: MIT
Platform: UNKNOWN
